routers_package_grocom/__init__.py
routers_package_grocom/backend.py
routers_package_grocom/base_views.py
routers_package_grocom/models.py
routers_package_grocom/routers.py
routers_package_grocom/serializer.py
routers_package_grocom/state.py
routers_package_grocom/tokens.py
routers_package-0.0.15.dist-info/LICENSE
routers_package-0.0.15.dist-info/METADATA
routers_package-0.0.15.dist-info/WHEEL
routers_package-0.0.15.dist-info/top_level.txt
routers_package-0.0.15.dist-info/RECORD
