Metadata-Version: 2.1
Name: routers-package
Version: 0.0.15
Summary: Package for routing grocom project
Classifier: Programming Language :: Python :: 3
Classifier: License :: OSI Approved :: MIT License
Classifier: Operating System :: OS Independent
Requires-Python: >=3.7
License-File: LICENSE
Requires-Dist: PyJWT
Requires-Dist: SQLAlchemy
Requires-Dist: python-dotenv
